setup.py
KeyLabs.egg-info/PKG-INFO
KeyLabs.egg-info/SOURCES.txt
KeyLabs.egg-info/dependency_links.txt
KeyLabs.egg-info/requires.txt
KeyLabs.egg-info/top_level.txt
keylabs/__init__.py
keylabs/client.py