Metadata-Version: 2.1
Name: KeyLabs
Version: 1.1
Summary: Api Wrapper for KeyLabs.cc
Home-page: UNKNOWN
Author: Psyro
License: UNKNOWN
Keywords: wrapper,apiwrapper,keylabs,auth,authsystem
Platform: UNKNOWN
Classifier: Intended Audience :: Developers
Classifier: Programming Language :: Python :: 3
Classifier: Operating System :: Unix
Classifier: Operating System :: MacOS :: MacOS X
Classifier: Operating System :: Microsoft :: Windows
